jupyterlab_nvdashboard/__init__.py
jupyterlab_nvdashboard/_version.py
jupyterlab_nvdashboard/handlers.py
jupyterlab_nvdashboard/apps/__init__.py
jupyterlab_nvdashboard/apps/cpu.py
jupyterlab_nvdashboard/apps/gpu.py
jupyterlab_nvdashboard/apps/utils.py
jupyterlab_nvdashboard/tests/conftest.py
jupyterlab_nvdashboard/tests/test_cpu_handlers.py
jupyterlab_nvdashboard/tests/test_gpu_handlers.py
jupyterlab_nvdashboard-0.13.0.data/data/etc/jupyter/jupyter_server_config.d/jupyterlab_nvdashboard.json
jupyterlab_nvdashboard-0.13.0.data/data/share/jupyter/labextensions/jupyterlab-nvdashboard/package.json
jupyterlab_nvdashboard-0.13.0.data/data/share/jupyter/labextensions/jupyterlab-nvdashboard/schemas/jupyterlab-nvdashboard/config.json
jupyterlab_nvdashboard-0.13.0.data/data/share/jupyter/labextensions/jupyterlab-nvdashboard/schemas/jupyterlab-nvdashboard/package.json.orig
jupyterlab_nvdashboard-0.13.0.data/data/share/jupyter/labextensions/jupyterlab-nvdashboard/static/142.aac70487eed3dc0a39d6.js
jupyterlab_nvdashboard-0.13.0.data/data/share/jupyter/labextensions/jupyterlab-nvdashboard/static/298.2d9444b80f7fcee893d3.js
jupyterlab_nvdashboard-0.13.0.data/data/share/jupyter/labextensions/jupyterlab-nvdashboard/static/369.8f073c2df448fc2193d0.js
jupyterlab_nvdashboard-0.13.0.data/data/share/jupyter/labextensions/jupyterlab-nvdashboard/static/481.c90ff39be4cb2b25d913.js
jupyterlab_nvdashboard-0.13.0.data/data/share/jupyter/labextensions/jupyterlab-nvdashboard/static/536.fe77b302b5119fae74e1.js
jupyterlab_nvdashboard-0.13.0.data/data/share/jupyter/labextensions/jupyterlab-nvdashboard/static/650.42c930a79dc805a3c9f3.js
jupyterlab_nvdashboard-0.13.0.data/data/share/jupyter/labextensions/jupyterlab-nvdashboard/static/650.42c930a79dc805a3c9f3.js.LICENSE.txt
jupyterlab_nvdashboard-0.13.0.data/data/share/jupyter/labextensions/jupyterlab-nvdashboard/static/747.f25177751d0f13ef3da0.js
jupyterlab_nvdashboard-0.13.0.dist-info/METADATA
jupyterlab_nvdashboard-0.13.0.dist-info/WHEEL
jupyterlab_nvdashboard-0.13.0.dist-info/licenses/LICENSE
jupyterlab_nvdashboard-0.13.0.dist-info/RECORD
