Metadata-Version: 2.4
Name: jupyterlab_nvdashboard
Version: 0.13.0
Dynamic: Keywords
Summary: A JupyterLab extension for displaying GPU usage dashboards
Project-URL: Homepage, https://github.com/rapidsai/jupyterlab-nvdashboard
Project-URL: Bug Tracker, https://github.com/rapidsai/jupyterlab-nvdashboard/issues
Project-URL: Repository, https://github.com/rapidsai/jupyterlab-nvdashboard.git
Author: NV Dashboard contributors
License: BSD 3-Clause License
License-File: LICENSE
Classifier: Framework :: Jupyter
Classifier: Framework :: Jupyter :: JupyterLab
Classifier: Framework :: Jupyter :: JupyterLab :: 4
Classifier: Framework :: Jupyter :: JupyterLab :: Extensions
Classifier: Framework :: Jupyter :: JupyterLab :: Extensions :: Prebuilt
Classifier: License :: OSI Approved :: BSD License
Classifier: Programming Language :: Python
Classifier: Programming Language :: Python :: 3
Classifier: Programming Language :: Python :: 3.8
Classifier: Programming Language :: Python :: 3.9
Classifier: Programming Language :: Python :: 3.10
Classifier: Programming Language :: Python :: 3.11
Classifier: Programming Language :: Python :: 3.12
Requires-Python: >=3.8
Requires-Dist: jupyterlab>=4
Requires-Dist: psutil
Requires-Dist: pynvml<13.0.0a0,>=12.0.0
Provides-Extra: test
Requires-Dist: pytest; extra == 'test'
Requires-Dist: pytest-asyncio; extra == 'test'
Requires-Dist: pytest-jupyter[server]>=0.6.0; extra == 'test'
Requires-Dist: websockets; extra == 'test'
